<?xml version='1.0' encoding='UTF-8'?>
<data xmlns="urn:ietf:params:xml:ns:netconf:base:1.0">
	<lldp xmlns="urn:ieee:std:802.1AB:yang:ieee802-dot1ab-lldp">
		<message-fast-tx></message-fast-tx>
		<message-tx-hold-multiplier></message-tx-hold-multiplier>
		<message-tx-interval></message-tx-interval>
		<reinit-delay></reinit-delay>
		<tx-credit-max></tx-credit-max>
		<tx-fast-init></tx-fast-init>
		<remote-statistics>
			<last-change-time/>
			<remote-inserts></remote-inserts>
			<remote-deletes></remote-deletes>
			<remote-drops></remote-drops>
			<remote-ageouts></remote-ageouts>
		</remote-statistics>
		<local-system-data>
			<chassis-id-subtype/>
			<chassis-id/>
			<system-name/>
			<system-description/>
			<system-capabilities-supported/>
			<system-capabilities-enabled/>
		</local-system-data>
		<port>
			<name/>
			<dest-mac-address/>
			<admin-status></admin-status>
			<tlvs-tx-enable/>
			<message-fast-tx></message-fast-tx>
			<message-tx-hold-multiplier></message-tx-hold-multiplier>
			<message-tx-interval></message-tx-interval>
			<reinit-delay></reinit-delay>
			<tx-credit-max></tx-credit-max>
			<tx-fast-init></tx-fast-init>
			<management-address-tx-port>
				<address-subtype/>
				<man-address/>
				<tx-enable></tx-enable>
				<addr-len/>
				<if-subtype/>
				<if-id/>
			</management-address-tx-port>
			<port-id-subtype/>
			<port-id/>
			<port-desc/>
			<tx-statistics>
				<total-frames/>
				<total-length-errors/>
			</tx-statistics>
			<rx-statistics>
				<total-ageouts></total-ageouts>
				<total-discarded-frames/>
				<error-frames/>
				<total-frames/>
				<total-discarded-tlvs/>
				<total-unrecognized-tlvs/>
			</rx-statistics>
			<remote-systems-data>
				<time-mark/>
				<remote-index/>
				<remote-too-many-neighbors/>
				<remote-changes/>
				<chassis-id-subtype/>
				<chassis-id/>
				<port-id-subtype/>
				<port-id/>
				<port-desc/>
				<system-name/>
				<system-description/>
				<system-capabilities-supported/>
				<system-capabilities-enabled/>
				<management-address>
					<address-subtype/>
					<address/>
					<if-subtype/>
					<if-id/>
				</management-address>
				<remote-unknown-tlv>
					<tlv-type/>
					<tlv-info/>
				</remote-unknown-tlv>
				<remote-org-defined-info>
					<info-identifier/>
					<info-subtype/>
					<info-index/>
					<remote-info/>
				</remote-org-defined-info>
			</remote-systems-data>
		</port>
	</lldp>
</data>
